loadsave/__init__.py
loadsave-0.0.3.dist-info/LICENSE
loadsave-0.0.3.dist-info/METADATA
loadsave-0.0.3.dist-info/WHEEL
loadsave-0.0.3.dist-info/top_level.txt
loadsave-0.0.3.dist-info/RECORD
