Metadata-Version: 2.1
Name: loadsave
Version: 0.0.3
Summary: One-line loading and saving to/from various file formats (csv, wav, pkl, json)
Home-page: https://github.com/JoelStansbury/Datastore
Author: Joel Stansbury
Author-email: stansbury.joel@gmail.com
License: UNKNOWN
Platform: UNKNOWN
Classifier: Programming Language :: Python :: 3
Classifier: License :: OSI Approved :: MIT License
Classifier: Operating System :: OS Independent
